cache_central_flush/__init__.py
cache_central_flush/async_flush.py
cache_central_flush/client.py
cache_central_flush-2.0.0.dist-info/LICENSE
cache_central_flush-2.0.0.dist-info/METADATA
cache_central_flush-2.0.0.dist-info/WHEEL
cache_central_flush-2.0.0.dist-info/top_level.txt
cache_central_flush-2.0.0.dist-info/RECORD
