Metadata-Version: 2.1
Name: cache-central-flush
Version: 2.0.0
Summary: Lightweight client package to asynchronously trigger centralized cache invalidation via API
Home-page: https://github.com/karantomar207/cache-central-flush
Author: Karan Singh Tomar
Author-email: karantomar207@gmail.com
License: MIT
Platform: UNKNOWN
Classifier: Development Status :: 4 - Beta
Classifier: Intended Audience :: Developers
Classifier: License :: OSI Approved :: MIT License
Classifier: Programming Language :: Python :: 3
Classifier: Programming Language :: Python :: 3.6
Classifier: Programming Language :: Python :: 3.7
Classifier: Programming Language :: Python :: 3.8
Classifier: Programming Language :: Python :: 3.9
Classifier: Programming Language :: Python :: 3.10
Classifier: Programming Language :: Python :: 3.11
Requires-Python: >=3.6
License-File: LICENSE
Requires-Dist: requests (<3,>=2.20)
